<?xml version="1.0" encoding="utf-8"?>
<Defs>
  <EffecterDef>
    <defName>BulletRicochetStoneWall</defName>
    <children>
      <li>
        <subEffecterClass>SubEffecter_SprayerChance</subEffecterClass>
        <moteDef>Mote_SparkFlash</moteDef>
        <spawnLocType>BetweenTouchingCells</spawnLocType>
        <positionLerpFactor>0.49</positionLerpFactor>
        <chancePerTick>0.2</chancePerTick>
        <scale>
          <min>2.5</min>
          <max>3.5</max>
        </scale>
      </li>
      <li>
        <subEffecterClass>SubEffecter_SprayerTriggered</subEffecterClass>
        <moteDef>Mote_SparkThrown</moteDef>
        <burstCount>
          <min>6</min>
          <max>12</max>
        </burstCount>
        <spawnLocType>OnSource</spawnLocType>
        <positionLerpFactor>0.49</positionLerpFactor>
        <chancePerTick>0.2</chancePerTick>
        <scale>
          <min>0.24</min>
          <max>0.34</max>
        </scale>
        <airTime>
          <min>0.08</min>
          <max>0.16</max>
        </airTime>
        <rotationRate>
          <min>-240</min>
          <max>240</max>
        </rotationRate>
        <speed>
          <min>7.2</min>
          <max>24</max>
        </speed>
        <angle>
          <min>135</min>
          <max>225</max>
        </angle>
        <positionRadius>0.02</positionRadius>
      </li>
    </children>
  </EffecterDef>
  <EffecterDef>
    <defName>BulletRicochetWoodWall</defName>
    <children>
      <li>
        <subEffecterClass>SubEffecter_SprayerTriggered</subEffecterClass>
        <moteDef>Mote_StoneBit</moteDef>
        <burstCount>
          <min>6</min>
          <max>12</max>
        </burstCount>
        <spawnLocType>OnSource</spawnLocType>
        <positionLerpFactor>0.49</positionLerpFactor>
        <chancePerTick>0.2</chancePerTick>
        <scale>
          <min>0.24</min>
          <max>0.34</max>
        </scale>
        <airTime>
          <min>0.08</min>
          <max>0.16</max>
        </airTime>
        <rotationRate>
          <min>-240</min>
          <max>240</max>
        </rotationRate>
        <speed>
          <min>7.2</min>
          <max>9.2</max>
        </speed>
        <angle>
          <min>135</min>
          <max>225</max>
        </angle>
        <positionRadius>0.02</positionRadius>
      </li>
    </children>
  </EffecterDef>
  <EffecterDef>
    <defName>BulletRicochetGround</defName>
    <children>
      <li>
        <subEffecterClass>SubEffecter_SprayerTriggered</subEffecterClass>
        <moteDef>Mote_BulletPuff</moteDef>
        <burstCount>
          <min>3</min>
          <max>7</max>
        </burstCount>
        <spawnLocType>OnSource</spawnLocType>
        <positionLerpFactor>0.49</positionLerpFactor>
        <chancePerTick>0.2</chancePerTick>
        <scale>
          <min>0.34</min>
          <max>1.3</max>
        </scale>
        <airTime>
          <min>1.2</min>
          <max>2.1</max>
        </airTime>
        <rotationRate>
          <min>-70</min>
          <max>70</max>
        </rotationRate>
        <speed>
          <min>0.7</min>
          <max>2.5</max>
        </speed>
        <angle>
          <min>70</min>
          <max>110</max>
        </angle>
        <positionRadius>0.02</positionRadius>
      </li>
    </children>
  </EffecterDef>
  <EffecterDef>
    <defName>BulletHitWallBuildingBits</defName>
    <children>
      <li>
        <subEffecterClass>SubEffecter_SprayerTriggered</subEffecterClass>
        <moteDef>Mote_BuildingBits</moteDef>
        <burstCount>
          <min>4</min>
          <max>9</max>
        </burstCount>
        <spawnLocType>OnSource</spawnLocType>
        <positionLerpFactor>0.49</positionLerpFactor>
        <chancePerTick>0.2</chancePerTick>
        <scale>
          <min>0.14</min>
          <max>0.34</max>
        </scale>
        <airTime>
          <min>0.08</min>
          <max>0.14</max>
        </airTime>
        <rotationRate>
          <min>-70</min>
          <max>70</max>
        </rotationRate>
        <speed>
          <min>1.2</min>
          <max>4.5</max>
        </speed>
        <angle>
          <min>0</min>
          <max>360</max>
        </angle>
        <positionRadius>0.32</positionRadius>
      </li>
    </children>
  </EffecterDef>
  <EffecterDef>
    <defName>BulletRicochetPuff</defName>
    <children>
      <li>
        <subEffecterClass>SubEffecter_SprayerTriggered</subEffecterClass>
        <moteDef>Mote_BulletPuff</moteDef>
        <burstCount>
          <min>3</min>
          <max>7</max>
        </burstCount>
        <spawnLocType>BetweenTouchingCells</spawnLocType>
        <positionLerpFactor>0.49</positionLerpFactor>
        <chancePerTick>0.2</chancePerTick>
        <scale>
          <min>0.34</min>
          <max>0.74</max>
        </scale>
        <airTime>
          <min>1.2</min>
          <max>2.1</max>
        </airTime>
        <rotationRate>
          <min>-70</min>
          <max>70</max>
        </rotationRate>
        <speed>
          <min>0.7</min>
          <max>2.5</max>
        </speed>
        <angle>
          <min>70</min>
          <max>110</max>
        </angle>
        <positionRadius>0.02</positionRadius>
      </li>
    </children>
  </EffecterDef>
</Defs>